{"name": "add", "children": [{"name": "egg", "children": [{"name": "bag", "children": [{"name": "corn", "children": [{"name": "corn", "value": 14}, {"name": "wedge", "value": 4}]}, {"name": "bag", "children": [{"name": "tangy", "value": 43}, {"name": "bag", "value": 5}]}, {"name": "burger", "children": [{"name": "burger", "value": 31}, {"name": "chickpea", "value": 56}]}, {"name": "air", "children": [{"name": "air", "value": 7}, {"name": "spray", "value": 10}, {"name": "granola", "value": 5}, {"name": "basket", "value": 21}]}]}, {"name": "cream", "children": [{"name": "french", "children": [{"name": "cube", "value": 6}, {"name": "french", "value": 2}, {"name": "night", "value": 16}, {"name": "breakfast", "value": 7}]}, {"name": "toast", "children": [{"name": "crunchy", "value": 24}, {"name": "toast", "value": 3}]}, {"name": "holiday", "children": [{"name": "pre", "value": 35}, {"name": "holiday", "value": 5}, {"name": "hole", "value": 14}]}, {"name": "milk", "children": [{"name": "icing", "value": 73}, {"name": "milk", "value": 3}]}, {"name": "chip", "children": [{"name": "chip", "value": 15}, {"name": "house", "value": 15}]}, {"name": "cream", "children": [{"name": "cream", "value": 3}]}]}, {"name": "ice", "children": [{"name": "rum", "children": [{"name": "whiskey", "value": 83}, {"name": "rum", "value": 67}, {"name": "san", "value": 16}, {"name": "infuse", "value": 5}]}, {"name": "drink", "children": [{"name": "vodka", "value": 263}, {"name": "drink", "value": 28}, {"name": "bottle", "value": 124}]}, {"name": "jelly", "children": [{"name": "jelly", "value": 59}, {"name": "rim", "value": 15}]}, {"name": "orange", "children": [{"name": "orange", "value": 5}, {"name": "pomegranate", "value": 41}, {"name": "watermelon", "value": 49}]}, {"name": "ice", "children": [{"name": "ice", "value": 1}, {"name": "almond", "value": 2}, {"name": "maker", "value": 25}]}, {"name": "cinnamon", "children": [{"name": "cardamom", "value": 9}, {"name": "nutmeg", "value": 8}, {"name": "cinnamon", "value": 8}, {"name": "oat", "value": 30}]}, {"name": "cranberry", "children": [{"name": "coffee", "value": 18}, {"name": "tea", "value": 34}, {"name": "cranberry", "value": 5}]}]}, {"name": "potato", "children": [{"name": "root", "children": [{"name": "sauerkraut", "value": 54}, {"name": "king", "value": 66}, {"name": "pear", "value": 33}, {"name": "beer", "value": 34}, {"name": "root", "value": 12}, {"name": "brick", "value": 53}]}, {"name": "potato", "children": [{"name": "potato", "value": 18}]}, {"name": "fork", "children": [{"name": "fork", "value": 6}, {"name": "chunk", "value": 5}]}]}, {"name": "egg", "children": [{"name": "bread", "children": [{"name": "sandwich", "value": 83}, {"name": "bread", "value": 8}]}, {"name": "egg", "children": [{"name": "egg", "value": 3}]}]}, {"name": "apple", "children": [{"name": "fruit", "children": [{"name": "fruit", "value": 17}, {"name": "peach", "value": 33}, {"name": "strawberry", "value": 16}, {"name": "jam", "value": 12}]}, {"name": "syrup", "children": [{"name": "syrup", "value": 14}]}, {"name": "biscuit", "children": [{"name": "cherry", "value": 8}, {"name": "biscuit", "value": 12}, {"name": "pancake", "value": 7}]}, {"name": "apple", "children": [{"name": "apple", "value": 15}]}]}, {"name": "cake", "children": [{"name": "cheesecake", "children": [{"name": "nutty", "value": 13}, {"name": "chewy", "value": 13}, {"name": "cracker", "value": 5}, {"name": "cheesecake", "value": 45}]}, {"name": "cookie", "children": [{"name": "caramel", "value": 40}, {"name": "chocolate", "value": 35}, {"name": "cookie", "value": 58}]}, {"name": "coconut", "children": [{"name": "peanut", "value": 17}, {"name": "frost", "value": 14}, {"name": "banana", "value": 26}, {"name": "coconut", "value": 1}]}, {"name": "whip", "children": [{"name": "crack", "value": 17}, {"name": "pudding", "value": 28}, {"name": "whip", "value": 31}, {"name": "dessert", "value": 31}]}, {"name": "beat", "children": [{"name": "beat", "value": 21}]}, {"name": "cake", "children": [{"name": "batter", "value": 10}, {"name": "muffin", "value": 7}, {"name": "cake", "value": 3}]}]}, {"name": "wrap", "children": [{"name": "wrap", "children": [{"name": "fill", "value": 5}, {"name": "tart", "value": 63}, {"name": "wrap", "value": 4}]}, {"name": "form", "children": [{"name": "form", "value": 10}, {"name": "shape", "value": 25}, {"name": "corner", "value": 37}]}]}, {"name": "dough", "children": [{"name": "flour", "children": [{"name": "flour", "value": 5}]}, {"name": "dough", "children": [{"name": "pie", "value": 8}, {"name": "dough", "value": 5}]}, {"name": "roll", "children": [{"name": "roll", "value": 5}, {"name": "rise", "value": 96}]}]}]}, {"name": "pepper", "children": [{"name": "grill", "children": [{"name": "meat", "children": [{"name": "beef", "value": 14}, {"name": "meat", "value": 5}, {"name": "pork", "value": 14}]}, {"name": "steak", "children": [{"name": "brine", "value": 28}, {"name": "rare", "value": 49}, {"name": "steak", "value": 12}, {"name": "sear", "value": 7}, {"name": "breast", "value": 36}, {"name": "marinade", "value": 7}]}, {"name": "fat", "children": [{"name": "fat", "value": 6}, {"name": "stew", "value": 38}]}, {"name": "roast", "children": [{"name": "roast", "value": 4}, {"name": "skin", "value": 4}]}, {"name": "towel", "children": [{"name": "towel", "value": 3}, {"name": "shallot", "value": 6}, {"name": "broiler", "value": 10}]}, {"name": "bone", "children": [{"name": "bone", "value": 8}, {"name": "hank", "value": 39}, {"name": "rib", "value": 15}, {"name": "tenderloin", "value": 9}, {"name": "lamb", "value": 21}]}, {"name": "grill", "children": [{"name": "grill", "value": 13}]}]}, {"name": "rice", "children": [{"name": "tomato", "children": [{"name": "bacon", "value": 4}, {"name": "tomato", "value": 3}]}, {"name": "skillet", "children": [{"name": "vegetable", "value": 2}, {"name": "skillet", "value": 2}]}, {"name": "rice", "children": [{"name": "rice", "value": 16}, {"name": "fry", "value": 11}]}, {"name": "chili", "children": [{"name": "jalape\u00f1o", "value": 14}, {"name": "mexican", "value": 46}, {"name": "chile", "value": 19}, {"name": "salsa", "value": 34}, {"name": "chili", "value": 1}, {"name": "cilantro", "value": 3}]}]}, {"name": "pressure", "children": [{"name": "wine", "children": [{"name": "cider", "value": 11}, {"name": "clove", "value": 23}, {"name": "wine", "value": 33}]}, {"name": "jar", "children": [{"name": "sour", "value": 2}, {"name": "strain", "value": 17}, {"name": "jar", "value": 17}, {"name": "lid", "value": 5}, {"name": "off", "value": 25}]}, {"name": "pressure", "children": [{"name": "hard", "value": 9}, {"name": "pressure", "value": 52}, {"name": "release", "value": 10}]}, {"name": "inside", "children": [{"name": "seal", "value": 25}, {"name": "sous", "value": 44}, {"name": "mold", "value": 37}, {"name": "outside", "value": 10}, {"name": "inside", "value": 18}]}, {"name": "soak", "children": [{"name": "pound", "value": 11}, {"name": "stuff", "value": 17}, {"name": "soak", "value": 3}, {"name": "skewer", "value": 21}]}]}, {"name": "pepper", "children": [{"name": "green", "children": [{"name": "green", "value": 1}, {"name": "drain", "value": 7}, {"name": "seasoning", "value": 10}, {"name": "parsley", "value": 6}]}, {"name": "pepper", "children": [{"name": "onion", "value": 1}, {"name": "garlic", "value": 7}, {"name": "pepper", "value": 3}]}]}]}, {"name": "chicken", "children": [{"name": "salad", "children": [{"name": "mustard", "children": [{"name": "cabbage", "value": 5}, {"name": "mustard", "value": 3}, {"name": "tuna", "value": 11}, {"name": "mayonnaise", "value": 14}, {"name": "dill", "value": 9}]}, {"name": "salad", "children": [{"name": "dressing", "value": 11}, {"name": "salad", "value": 10}]}, {"name": "wing", "children": [{"name": "wing", "value": 28}, {"name": "poach", "value": 20}]}, {"name": "cucumber", "children": [{"name": "cucumber", "value": 30}, {"name": "macaroni", "value": 21}]}]}, {"name": "avocado", "children": [{"name": "pickle", "children": [{"name": "pickle", "value": 6}, {"name": "pineapple", "value": 3}]}, {"name": "avocado", "children": [{"name": "ripe", "value": 23}, {"name": "avocado", "value": 2}, {"name": "mango", "value": 19}]}, {"name": "nut", "children": [{"name": "nut", "value": 4}, {"name": "pesto", "value": 6}]}]}, {"name": "cooker", "children": [{"name": "cooker", "children": [{"name": "slow", "value": 3}, {"name": "cooker", "value": 2}]}, {"name": "blender", "children": [{"name": "blender", "value": 6}, {"name": "squash", "value": 7}]}, {"name": "seed", "children": [{"name": "seed", "value": 2}, {"name": "pumpkin", "value": 6}]}]}, {"name": "spice", "children": [{"name": "spice", "children": [{"name": "spice", "value": 4}, {"name": "yogurt", "value": 22}, {"name": "honey", "value": 10}]}, {"name": "ginger", "children": [{"name": "curry", "value": 58}, {"name": "sieve", "value": 7}, {"name": "ginger", "value": 3}]}]}, {"name": "mushroom", "children": [{"name": "mushroom", "children": [{"name": "baby", "value": 8}, {"name": "mushroom", "value": 14}]}, {"name": "turkey", "children": [{"name": "cornmeal", "value": 27}, {"name": "gravy", "value": 10}, {"name": "flesh", "value": 5}, {"name": "turkey", "value": 2}]}, {"name": "casserole", "children": [{"name": "casserole", "value": 30}, {"name": "iron", "value": 2}]}]}, {"name": "shrimp", "children": [{"name": "wild", "children": [{"name": "plantain", "value": 178}, {"name": "culture", "value": 100}, {"name": "wild", "value": 71}, {"name": "oyster", "value": 151}, {"name": "rabbit", "value": 22}]}, {"name": "pur\u00e9e", "children": [{"name": "pur\u00e9e", "value": 5}, {"name": "blondie", "value": 153}, {"name": "parsnip", "value": 23}, {"name": "grit", "value": 148}]}, {"name": "shrimp", "children": [{"name": "roux", "value": 18}, {"name": "clam", "value": 63}, {"name": "shrimp", "value": 48}, {"name": "crab", "value": 26}, {"name": "shell", "value": 36}]}]}, {"name": "chicken", "children": [{"name": "soup", "children": [{"name": "stock", "value": 3}, {"name": "broth", "value": 11}, {"name": "soup", "value": 16}]}, {"name": "chicken", "children": [{"name": "chicken", "value": 7}]}]}, {"name": "pasta", "children": [{"name": "spinach", "children": [{"name": "beet", "value": 30}, {"name": "kale", "value": 32}, {"name": "wilt", "value": 6}, {"name": "chard", "value": 11}, {"name": "spinach", "value": 9}]}, {"name": "pasta", "children": [{"name": "pasta", "value": 67}, {"name": "noodle", "value": 26}]}]}, {"name": "sausage", "children": [{"name": "sausage", "children": [{"name": "caramelize", "value": 8}, {"name": "sausage", "value": 3}, {"name": "grated", "value": 4}]}, {"name": "pizza", "children": [{"name": "gnocchi", "value": 22}, {"name": "pizza", "value": 56}, {"name": "glaze", "value": 3}, {"name": "meatball", "value": 18}]}, {"name": "parmesan", "children": [{"name": "ricotta", "value": 9}, {"name": "parmesan", "value": 9}, {"name": "zucchini", "value": 14}]}]}, {"name": "vinegar", "children": [{"name": "pea", "children": [{"name": "pea", "value": 19}, {"name": "vegetarian", "value": 33}, {"name": "quinoa", "value": 28}]}, {"name": "ham", "children": [{"name": "ham", "value": 17}, {"name": "artichoke", "value": 13}, {"name": "asparagus", "value": 10}]}, {"name": "vinegar", "children": [{"name": "vinegar", "value": 2}, {"name": "eggplant", "value": 10}]}, {"name": "cauliflower", "children": [{"name": "sprout", "value": 35}, {"name": "head", "value": 5}, {"name": "cauliflower", "value": 4}, {"name": "broccoli", "value": 10}]}, {"name": "dip", "children": [{"name": "dip", "value": 2}, {"name": "fennel", "value": 31}]}]}, {"name": "fish", "children": [{"name": "fish", "children": [{"name": "fish", "value": 75}, {"name": "salmon", "value": 9}]}, {"name": "paste", "children": [{"name": "thai", "value": 24}, {"name": "paste", "value": 5}]}, {"name": "soy", "children": [{"name": "soy", "value": 59}]}]}, {"name": "bean", "children": [{"name": "bean", "children": [{"name": "bean", "value": 17}]}, {"name": "tortilla", "children": [{"name": "taco", "value": 11}, {"name": "tortilla", "value": 13}, {"name": "leek", "value": 7}]}]}]}, {"name": "add", "children": [{"name": "sauce", "children": [{"name": "melt", "children": [{"name": "pop", "value": 36}, {"name": "double", "value": 24}, {"name": "microwave", "value": 11}, {"name": "second", "value": 3}, {"name": "melt", "value": 4}]}, {"name": "sauce", "children": [{"name": "dish", "value": 1}, {"name": "sauce", "value": 2}]}, {"name": "piece", "children": [{"name": "piece", "value": 1}, {"name": "spread", "value": 6}, {"name": "kid", "value": 67}, {"name": "absorb", "value": 18}, {"name": "bite", "value": 4}]}, {"name": "pour", "children": [{"name": "white", "value": 3}, {"name": "base", "value": 8}, {"name": "pour", "value": 4}, {"name": "thicken", "value": 10}, {"name": "saucepan", "value": 16}, {"name": "chill", "value": 2}]}, {"name": "ground", "children": [{"name": "mint", "value": 15}, {"name": "clear", "value": 48}, {"name": "package", "value": 10}, {"name": "pack", "value": 17}, {"name": "ground", "value": 5}, {"name": "can", "value": 11}]}, {"name": "food", "children": [{"name": "thick", "value": 3}, {"name": "press", "value": 14}, {"name": "food", "value": 6}]}, {"name": "red", "children": [{"name": "red", "value": 3}, {"name": "spicy", "value": 14}, {"name": "smoke", "value": 32}, {"name": "lime", "value": 7}]}, {"name": "toss", "children": [{"name": "peel", "value": 7}, {"name": "toss", "value": 3}, {"name": "discard", "value": 11}, {"name": "summer", "value": 45}]}, {"name": "juice", "children": [{"name": "zest", "value": 10}, {"name": "juice", "value": 2}, {"name": "lemon", "value": 3}]}, {"name": "cheese", "children": [{"name": "cheese", "value": 6}, {"name": "crispy", "value": 11}]}, {"name": "sugar", "children": [{"name": "dark", "value": 21}, {"name": "sugar", "value": 4}, {"name": "vanilla", "value": 9}]}, {"name": "mixture", "children": [{"name": "whisk", "value": 25}, {"name": "cup", "value": 3}, {"name": "mixture", "value": 1}, {"name": "free", "value": 93}]}, {"name": "butter", "children": [{"name": "brown", "value": 3}, {"name": "butter", "value": 2}]}]}, {"name": "add", "children": [{"name": "recipe", "children": [{"name": "day", "value": 4}, {"name": "as", "value": 3}, {"name": "eat", "value": 25}, {"name": "find", "value": 6}, {"name": "feel", "value": 20}, {"name": "great", "value": 7}, {"name": "call", "value": 57}, {"name": "look", "value": 14}, {"name": "delicious", "value": 14}, {"name": "recipe", "value": 1}, {"name": "transfer", "value": 10}, {"name": "easy", "value": 3}, {"name": "love", "value": 4}, {"name": "turn", "value": 5}, {"name": "remove", "value": 2}, {"name": "set", "value": 3}, {"name": "extra", "value": 19}, {"name": "link", "value": 36}, {"name": "flavor", "value": 15}, {"name": "long", "value": 7}, {"name": "let", "value": 1}, {"name": "bowl", "value": 1}]}, {"name": "add", "children": [{"name": "add", "value": 8}, {"name": "aroma", "value": 6546}, {"name": "cook", "value": 5}]}, {"name": "cover", "children": [{"name": "own", "value": 16}, {"name": "choice", "value": 45}, {"name": "one", "value": 16}, {"name": "\u2019", "value": 9}, {"name": "home", "value": 34}, {"name": "book", "value": 96}, {"name": "slightly", "value": 53}, {"name": "new", "value": 48}, {"name": "such", "value": 32}, {"name": "help", "value": 5}, {"name": "father", "value": 30}, {"name": "together", "value": 4}, {"name": "bitter", "value": 58}, {"name": "leave", "value": 3}, {"name": "end", "value": 9}, {"name": "small", "value": 3}, {"name": "back", "value": 15}, {"name": "allow", "value": 12}, {"name": "sure", "value": 12}, {"name": "warm", "value": 4}, {"name": "simple", "value": 11}, {"name": "stick", "value": 25}, {"name": "store", "value": 17}, {"name": "version", "value": 13}, {"name": "low", "value": 3}, {"name": "cover", "value": 1}, {"name": "buy", "value": 21}, {"name": "year", "value": 8}, {"name": "perfect", "value": 13}, {"name": "spoon", "value": 5}, {"name": "mix", "value": 4}, {"name": "include", "value": 31}, {"name": "again", "value": 13}, {"name": "all", "value": 8}, {"name": "soft", "value": 8}, {"name": "away", "value": 11}, {"name": "gently", "value": 7}, {"name": "combine", "value": 10}, {"name": "half", "value": 2}]}]}, {"name": "make", "children": [{"name": "make", "children": [{"name": "have", "value": 73}, {"name": "use", "value": 28}, {"name": "make", "value": 36}]}]}, {"name": "pan", "children": [{"name": "pot", "children": [{"name": "pot", "value": 2}, {"name": "tender", "value": 8}, {"name": "cooking", "value": 5}, {"name": "simmer", "value": 3}]}, {"name": "ingredient", "children": [{"name": "drop", "value": 37}, {"name": "color", "value": 18}, {"name": "texture", "value": 6}, {"name": "ingredient", "value": 4}, {"name": "sweet", "value": 1}, {"name": "light", "value": 10}, {"name": "creamy", "value": 10}, {"name": "smooth", "value": 2}, {"name": "container", "value": 6}, {"name": "batch", "value": 3}]}, {"name": "pan", "children": [{"name": "salt", "value": 3}, {"name": "pan", "value": 1}]}, {"name": "place", "children": [{"name": "place", "value": 1}, {"name": "inch", "value": 5}, {"name": "slice", "value": 3}, {"name": "top", "value": 1}]}, {"name": "layer", "children": [{"name": "center", "value": 17}, {"name": "fold", "value": 6}, {"name": "foil", "value": 11}, {"name": "rack", "value": 12}, {"name": "paper", "value": 7}, {"name": "layer", "value": 5}, {"name": "line", "value": 8}, {"name": "edge", "value": 5}]}, {"name": "cool", "children": [{"name": "hand", "value": 8}, {"name": "bottom", "value": 3}, {"name": "cool", "value": 4}, {"name": "temperature", "value": 5}, {"name": "freeze", "value": 4}]}, {"name": "side", "children": [{"name": "cut", "value": 18}, {"name": "sprinkle", "value": 7}, {"name": "side", "value": 7}]}, {"name": "hour", "children": [{"name": "hour", "value": 2}, {"name": "least", "value": 5}, {"name": "tip", "value": 21}, {"name": "dry", "value": 1}, {"name": "refrigerator", "value": 3}]}, {"name": "chop", "children": [{"name": "chop", "value": 1}, {"name": "leftover", "value": 3}, {"name": "saut\u00e9", "value": 10}, {"name": "coat", "value": 8}]}, {"name": "serve", "children": [{"name": "serve", "value": 3}, {"name": "stir", "value": 5}]}, {"name": "oven", "children": [{"name": "bake", "value": 5}, {"name": "baking", "value": 4}, {"name": "oven", "value": 3}]}, {"name": "water", "children": [{"name": "taste", "value": 6}, {"name": "water", "value": 2}, {"name": "boil", "value": 6}, {"name": "fresh", "value": 8}]}, {"name": "oil", "children": [{"name": "meal", "value": 23}, {"name": "oil", "value": 3}]}, {"name": "hot", "children": [{"name": "method", "value": 12}, {"name": "rest", "value": 7}, {"name": "hot", "value": 5}, {"name": "thermometer", "value": 13}, {"name": "begin", "value": 10}]}]}]}]}